{
  "purchases": [
    {
      "id": "OUT1622481957",
      "total_price": 2876,
      "total_item": 4,
      "date": "2021-05-31 23:11:20",
      "is_cash": "Pay Later",
      "pay_deadline_date": "2021-06-30",
      "supplier_id": "CUST0027",
      "supplier_name": "Terra Martin",
      "supplier_phone": 2457000026,
      "supplier_address": "Terra C Martin",
      "category_name": "Smart Phones",
      "product_id": "GP05",
      "product_name": "Google Pixel 5",
      "product_desc": "Dimensions: 144.7mm x 70.4mm x 8mm, OS: Android 11, Screen size: 6-inch, Resolution: 2340 x 1080, CPU: Snapdragon 765G, RAM: 8GB, Storage: 128GB, Battery: 4000mAh, Rear camera: 16MP + 12MP, Front camera: 8MP",
      "quantity": 4,
      "price_item": 719,
      "subtotal": 2876
    },
    {
      "id": "OUT1622481902",
      "total_price": 6657,
      "total_item": 3,
      "date": "2021-05-31 23:10:14",
      "is_cash": "Pay Later",
      "pay_deadline_date": "2021-06-30",
      "supplier_id": "CUST0026",
      "supplier_name": "Craig Cervantes",
      "supplier_phone": 4012586960,
      "supplier_address": "1231  Gregory Lane",
      "category_name": "Computers",
      "product_id": "DPT7",
      "product_name": "Dell Precision 7920 Tower",
      "product_desc": "Dual-CPU monster for tasks that can leverage its server-grade hardware and require maximum reliability. Just be prepared for sticker shock if you go all-in like on our test model.",
      "quantity": 3,
      "price_item": 2219,
      "subtotal": 6657
    },
    {
      "id": "OUT1622481877",
      "total_price": 11085,
      "total_item": 3,
      "date": "2021-05-31 23:09:50",
      "is_cash": "Pay Later",
      "pay_deadline_date": "2021-06-30",
      "supplier_id": "CUST0025",
      "supplier_name": "Barbara Richmond",
      "supplier_phone": 4545754210,
      "supplier_address": "3170  Andell Road",
      "category_name": "Computers",
      "product_id": "MSS2",
      "product_name": "Microsoft Surface Studio 2",
      "product_desc": "Microsoft Surface Studio 2 is a beautiful, pricey all-in-one desktop for artists, content creators, and professionals wedded to pen input. It packs components peppier than the originals, and a downright stunning screen.",
      "quantity": 3,
      "price_item": 3695,
      "subtotal": 11085
    },
    {
      "id": "OUT1622481746",
      "total_price": 9692,
      "total_item": 4,
      "date": "2021-05-31 23:07:44",
      "is_cash": "Cash",
      "pay_deadline_date": "",
      "supplier_id": "CUST0024",
      "supplier_name": "Dale C Garcia",
      "supplier_phone": 8012224570,
      "supplier_address": "1989  Grasselli Street",
      "category_name": "Computers",
      "product_id": "AR79",
      "product_name": "Alienware Aurora Ryzen Edition R10",
      "product_desc": "CPU: Up to AMD Ryzen 9 5950X, Graphics: Up to NVIDIA GeForce RTX 3080, RAM: Up to 128GB 3200MHz DDR4, Storage: Up to 2TB SSD + 2TB HDD",
      "quantity": 4,
      "price_item": 2423,
      "subtotal": 9692
    },
    {
      "id": "OUT1622481728",
      "total_price": 3084,
      "total_item": 6,
      "date": "2021-05-31 23:07:24",
      "is_cash": "Pay Later",
      "pay_deadline_date": "2021-06-30",
      "supplier_id": "CUST0023",
      "supplier_name": "Juan J Keyes",
      "supplier_phone": 1457000010,
      "supplier_address": "3287  Grove Avenue",
      "category_name": "Console",
      "product_id": "XSX9",
      "product_name": "Xbox Series X",
      "product_desc": "CPU: 8x Cores @ 3.8 GHz (3.6 GHz w/ SMT) Custom Zen 2 CPU, GPU: 12 TFLOPS, 52 CUs @ 1.825 GHz Custom RDNA 2 GPU, Die Size: 360.45 mm2, Process: 7nm Enhanced, Memory: 16 GB GDDR6 w/ 320b bus, Memory Bandwidth: 10GB @ 560 GB/s, 6GB @ 336 GB/s",
      "quantity": 6,
      "price_item": 514,
      "subtotal": 3084
    },
    {
      "id": "OUT1622481666",
      "total_price": 9996,
      "total_item": 4,
      "date": "2021-05-31 23:06:19",
      "is_cash": "Pay Later",
      "pay_deadline_date": "2021-06-30",
      "supplier_id": "CUST0022",
      "supplier_name": "Philip Gheek",
      "supplier_phone": 7000024500,
      "supplier_address": "2091  Trainer Avenue",
      "category_name": "Smart TV",
      "product_id": "LGC1",
      "product_name": "LG C1 OLED Series",
      "product_desc": "Screen size: 48-inch, 55-inch, 65-inch, 77-inch, Resolution: 4K, Panel type: OLED, Smart TV: webOS, HDR: HDR, HLG, Dolby Vision",
      "quantity": 4,
      "price_item": 2499,
      "subtotal": 9996
    },
    {
      "id": "OUT1622481594",
      "total_price": 7473,
      "total_item": 3,
      "date": "2021-05-31 23:05:06",
      "is_cash": "Pay Later",
      "pay_deadline_date": "2021-06-30",
      "supplier_id": "CUST0021",
      "supplier_name": "William J Beck",
      "supplier_phone": 7350002140,
      "supplier_address": "4665  Lunetta Street",
      "category_name": "Smart TV",
      "product_id": "LGC1",
      "product_name": "LG C1 OLED Series",
      "product_desc": "Screen size: 48-inch, 55-inch, 65-inch, 77-inch, Resolution: 4K, Panel type: OLED, Smart TV: webOS, HDR: HDR, HLG, Dolby Vision",
      "quantity": 3,
      "price_item": 2491,
      "subtotal": 7473
    },
    {
      "id": "OUT1622481459",
      "total_price": 5260,
      "total_item": 4,
      "date": "2021-05-31 23:03:35",
      "is_cash": "Pay Later",
      "pay_deadline_date": "2021-06-30",
      "supplier_id": "CUST0020",
      "supplier_name": "Charles Thompson",
      "supplier_phone": 7014200010,
      "supplier_address": "3628  Radio Park Drive",
      "category_name": "Console",
      "product_id": "PS05",
      "product_name": "PlayStation 5",
      "product_desc": "CPU: AMD Zen 2-based CPU with 8 cores at 3.5GHz (variable frequency), GPU: 10.28 TFLOPs, 36 CUs at 2.23GHz (variable frequency), Memory bandwidth: 448GB/s, Internal storage: Custom 825GB SSD, Optical Drive: 4K UHD Blu-ray Drive (for standard edition)",
      "quantity": 4,
      "price_item": 1315,
      "subtotal": 5260
    },
    {
      "id": "OUT1622481388",
      "total_price": 1440,
      "total_item": 72,
      "date": "2021-05-31 23:01:56",
      "is_cash": "Pay Later",
      "pay_deadline_date": "2021-06-30",
      "supplier_id": "CUST0019",
      "supplier_name": "Jay Deen",
      "supplier_phone": 7026000021,
      "supplier_address": "2685  Meadow View Drive",
      "category_name": "Clothing - Men",
      "product_id": "BJ02",
      "product_name": "Plaid Denim Jacket",
      "product_desc": "Turn-Down Collar, Safari Jacket, Style: Casual, Color-Block Design, Sustainable, Quick Dry, Breathable, Plain Dyed, Thickness: Regular, Pattern Type: Striped, Size up to 3XL",
      "quantity": 72,
      "price_item": 20,
      "subtotal": 1440
    },
    {
      "id": "OUT1622480604",
      "total_price": 12754,
      "total_item": 10,
      "date": "2021-05-31 22:53:05",
      "is_cash": "Cash",
      "pay_deadline_date": "",
      "supplier_id": "CUST0007",
      "supplier_name": "Liam Moore",
      "supplier_phone": 7901250001,
      "supplier_address": "316  Meadowview Drive",
      "category_name": "Smart Phones",
      "product_id": "SG21",
      "product_name": "Samsung Galaxy S21 Ultra",
      "product_desc": "Weight: 227g, Dimensions: 165.1 x 75.6 x 8.9 mm, OS: Android 11, Screen size: 6.8-inch, Resolution: 1440 x 3200, CPU: Snapdragon 888 / Exynos 2100, RAM: 12GB / 16GB, Storage: 128GB/256GB/512GB, Battery: 5,000mAh, Rear camera: 108MP + 10MP + 10MP + 12MP, Front camera: 40MP",
      "quantity": 6,
      "price_item": 1193,
      "subtotal": 7158
    },
    {
      "id": "",
      "total_price": "",
      "total_item": "",
      "date": "",
      "is_cash": "",
      "pay_deadline_date": "",
      "supplier_id": "",
      "supplier_name": "",
      "supplier_phone": "",
      "supplier_address": "",
      "category_name": "",
      "product_id": "IP12",
      "product_name": "iPhone 12 Pro Max",
      "product_desc": "Dimensions: 146.7mm x 71.5mm x 7.4 mm / 160.8mm x 78.1mm x 7.4mm, OS: iOS 14, Screen size: 6.1-inch / 6.7-inch, Resolution: 1170 x 2532 / 1284 x 2778, CPU: A14 Bionic, RAM: 6GB, Storage: 128GB/256GB/512GB, Rear camera: 12MP + 12MP + 12MP, Front camera: 12MP",
      "quantity": 4,
      "price_item": 1399,
      "subtotal": 5596
    },
    {
      "id": "OUT1622480676",
      "total_price": 11545,
      "total_item": 5,
      "date": "2021-05-31 22:49:51",
      "is_cash": "Cash",
      "pay_deadline_date": "",
      "supplier_id": "CUST0013",
      "supplier_name": "John Stuart",
      "supplier_phone": 4570002147,
      "supplier_address": "144  Owagner Lane",
      "category_name": "Smart TV",
      "product_id": "SQ80",
      "product_name": "Samsung Q80T QLED",
      "product_desc": "Screen Size: 75-inch, Resolution: 4K, Panel Type: QLED, Smart TV: Tizen, HDR: HDR10, HLG, HDR10+",
      "quantity": 5,
      "price_item": 2309,
      "subtotal": 11545
    },
    {
      "id": "OUT1622480447",
      "total_price": 27913,
      "total_item": 16,
      "date": "2021-05-31 22:46:54",
      "is_cash": "Cash",
      "pay_deadline_date": "",
      "supplier_id": "CUST0018",
      "supplier_name": "Elaine Nelson",
      "supplier_phone": 7016969650,
      "supplier_address": "1061 Black Stallion Road",
      "category_name": "Console",
      "product_id": "PS05",
      "product_name": "PlayStation 5",
      "product_desc": "CPU: AMD Zen 2-based CPU with 8 cores at 3.5GHz (variable frequency), GPU: 10.28 TFLOPs, 36 CUs at 2.23GHz (variable frequency), Memory bandwidth: 448GB/s, Internal storage: Custom 825GB SSD, Optical Drive: 4K UHD Blu-ray Drive (for standard edition)",
      "quantity": 7,
      "price_item": 1310,
      "subtotal": 9170
    },
    {
      "id": "",
      "total_price": "",
      "total_item": "",
      "date": "",
      "is_cash": "",
      "pay_deadline_date": "",
      "supplier_id": "",
      "supplier_name": "",
      "supplier_phone": "",
      "supplier_address": "",
      "category_name": "",
      "product_id": "SQ80",
      "product_name": "Samsung Q80T QLED",
      "product_desc": "Screen Size: 75-inch, Resolution: 4K, Panel Type: QLED, Smart TV: Tizen, HDR: HDR10, HLG, HDR10+",
      "quantity": 5,
      "price_item": 2299,
      "subtotal": 11495
    },
    {
      "id": "",
      "total_price": "",
      "total_item": "",
      "date": "",
      "is_cash": "",
      "pay_deadline_date": "",
      "supplier_id": "",
      "supplier_name": "",
      "supplier_phone": "",
      "supplier_address": "",
      "category_name": "",
      "product_id": "SALD",
      "product_name": "Sony A8H OLED",
      "product_desc": "Screen size: 55-inch, 65-inchResolution: 4K, Panel Type: OLED, Smart TV: Android TV, HDR: HDR10, HLG, Dolby Vision",
      "quantity": 4,
      "price_item": 1812,
      "subtotal": 7248
    },
    {
      "id": "OUT1622477417",
      "total_price": 2478,
      "total_item": 2,
      "date": "2021-05-31 21:55:40",
      "is_cash": "Pay Later",
      "pay_deadline_date": "2021-06-30",
      "supplier_id": "CUST0014",
      "supplier_name": "Franklin Morris",
      "supplier_phone": 7854745444,
      "supplier_address": "1305  Fulton Street",
      "category_name": "Smart Phones",
      "product_id": "SGN6",
      "product_name": "Samsung Galaxy Note 20 Ultra",
      "product_desc": "Dimensions: 164.8 x 77.2 x 8.1mm, OS: Android 10, Screen size: 6.9-inch, CPU: Exynos 990 / Snapdragon 865 Plus, RAM: 12GB, Storage: 128GB/256/512GB, Battery: 4,500mAh, Rear camera: 108MP/12MP + 12MP + 12MP, Front camera: 10MP",
      "quantity": 2,
      "price_item": 1239,
      "subtotal": 2478
    },
    {
      "id": "OUT1622477318",
      "total_price": 8398,
      "total_item": 2,
      "date": "2021-05-31 21:53:56",
      "is_cash": "Cash",
      "pay_deadline_date": "",
      "supplier_id": "CUST0009",
      "supplier_name": "Margaret Pfiefer",
      "supplier_phone": 7373569690,
      "supplier_address": "15  Broadway Street",
      "category_name": "Smart TV",
      "product_id": "QN95",
      "product_name": "Samsung QN95A Neo QLED",
      "product_desc": "Screen size: 75-inch, Resolution: 4K, Panel technology: Neo QLED, Smart TV: Tizen, HDR: HDR10, HLG, HDR10+",
      "quantity": 2,
      "price_item": 4199,
      "subtotal": 8398
    },
    {
      "id": "OUT1622477202",
      "total_price": 24,
      "total_item": 1,
      "date": "2021-05-31 21:52:15",
      "is_cash": "Cash",
      "pay_deadline_date": "",
      "supplier_id": "CUST0008",
      "supplier_name": "Michael E Dorsey",
      "supplier_phone": 7031456550,
      "supplier_address": "3758  Turkey Pen Lane",
      "category_name": "Clothing - Men",
      "product_id": "SJ20",
      "product_name": "Sweat Suit Jogger Sets",
      "product_desc": "QUICK DRY, Breathable, Plus Size, Fashion Comfortable, Size up to 3XL, Type: Training & Jogging Wear, Age Group: Adults, Product Type: Street Wear",
      "quantity": 1,
      "price_item": 24,
      "subtotal": 24
    },
    {
      "id": "OUT1622477140",
      "total_price": 4212,
      "total_item": 234,
      "date": "2021-05-31 21:51:37",
      "is_cash": "Pay Later",
      "pay_deadline_date": "2021-06-30",
      "supplier_id": "CUST0015",
      "supplier_name": "Esther Keene",
      "supplier_phone": 7021245855,
      "supplier_address": "2419  Woodridge Lane",
      "category_name": "Clothing - Men",
      "product_id": "BJ02",
      "product_name": "Plaid Denim Jacket",
      "product_desc": "Turn-Down Collar, Safari Jacket, Style: Casual, Color-Block Design, Sustainable, Quick Dry, Breathable, Plain Dyed, Thickness: Regular, Pattern Type: Striped, Size up to 3XL",
      "quantity": 234,
      "price_item": 18,
      "subtotal": 4212
    },
    {
      "id": "OUT1622477105",
      "total_price": 152,
      "total_item": 10,
      "date": "2021-05-31 21:50:31",
      "is_cash": "Cash",
      "pay_deadline_date": "",
      "supplier_id": "CUST0017",
      "supplier_name": "Andrea Hernandez",
      "supplier_phone": 7034786540,
      "supplier_address": "4717  Swick Hill Street",
      "category_name": "Clothing - Men",
      "product_id": "SJ20",
      "product_name": "Sweat Suit Jogger Sets",
      "product_desc": "QUICK DRY, Breathable, Plus Size, Fashion Comfortable, Size up to 3XL, Type: Training & Jogging Wear, Age Group: Adults, Product Type: Street Wear",
      "quantity": 4,
      "price_item": 23,
      "subtotal": 92
    },
    {
      "id": "",
      "total_price": "",
      "total_item": "",
      "date": "",
      "is_cash": "",
      "pay_deadline_date": "",
      "supplier_id": "",
      "supplier_name": "",
      "supplier_phone": "",
      "supplier_address": "",
      "category_name": "",
      "product_id": "TD02",
      "product_name": "Tie Dye T Shirts",
      "product_desc": "Multi-Colored, 100% Cotton, O-Neck Collar, Tie-Dye Design, Drop Shoulder Design, Short Sleeves, Fabric Weight: 160 grams, Size up to 3XL",
      "quantity": 6,
      "price_item": 10,
      "subtotal": 60
    },
    {
      "id": "OUT1622476825",
      "total_price": 1038,
      "total_item": 2,
      "date": "2021-05-31 21:45:49",
      "is_cash": "Cash",
      "pay_deadline_date": "",
      "supplier_id": "CUST0005",
      "supplier_name": "Eloise Gilliam",
      "supplier_phone": 7014741400,
      "supplier_address": "3358  Hillcrest Drive",
      "category_name": "Console",
      "product_id": "XSX9",
      "product_name": "Xbox Series X",
      "product_desc": "CPU: 8x Cores @ 3.8 GHz (3.6 GHz w/ SMT) Custom Zen 2 CPU, GPU: 12 TFLOPS, 52 CUs @ 1.825 GHz Custom RDNA 2 GPU, Die Size: 360.45 mm2, Process: 7nm Enhanced, Memory: 16 GB GDDR6 w/ 320b bus, Memory Bandwidth: 10GB @ 560 GB/s, 6GB @ 336 GB/s",
      "quantity": 2,
      "price_item": 519,
      "subtotal": 1038
    },
    {
      "id": "OUT1622476577",
      "total_price": 2157,
      "total_item": 3,
      "date": "2021-05-31 21:41:48",
      "is_cash": "Cash",
      "pay_deadline_date": "",
      "supplier_id": "CUST0012",
      "supplier_name": "Anthony Farrell",
      "supplier_phone": 7014741450,
      "supplier_address": "1445  Bridge Street",
      "category_name": "Smart Phones",
      "product_id": "GP05",
      "product_name": "Google Pixel 5",
      "product_desc": "Dimensions: 144.7mm x 70.4mm x 8mm, OS: Android 11, Screen size: 6-inch, Resolution: 2340 x 1080, CPU: Snapdragon 765G, RAM: 8GB, Storage: 128GB, Battery: 4000mAh, Rear camera: 16MP + 12MP, Front camera: 8MP",
      "quantity": 3,
      "price_item": 719,
      "subtotal": 2157
    },
    {
      "id": "OUT1622472766",
      "total_price": 5697,
      "total_item": 3,
      "date": "2021-05-31 20:38:07",
      "is_cash": "Pay Later",
      "pay_deadline_date": "2021-06-30",
      "supplier_id": "CUST0016",
      "supplier_name": "Samuel Julius",
      "supplier_phone": 7036985421,
      "supplier_address": "2290  Clarence Court",
      "category_name": "Smart TV",
      "product_id": "SALD",
      "product_name": "Sony A8H OLED",
      "product_desc": "Screen size: 55-inch, 65-inchResolution: 4K, Panel Type: OLED, Smart TV: Android TV, HDR: HDR10, HLG, Dolby Vision",
      "quantity": 3,
      "price_item": 1899,
      "subtotal": 5697
    },
    {
      "id": "OUT1622472410",
      "total_price": 152,
      "total_item": 8,
      "date": "2021-05-31 20:32:11",
      "is_cash": "Cash",
      "pay_deadline_date": "",
      "supplier_id": "CUST0006",
      "supplier_name": "Benjamin F Phillip",
      "supplier_phone": 7023565680,
      "supplier_address": "3404  Carter Street",
      "category_name": "Clothing - Men",
      "product_id": "BJ02",
      "product_name": "Plaid Denim Jacket",
      "product_desc": "Turn-Down Collar, Safari Jacket, Style: Casual, Color-Block Design, Sustainable, Quick Dry, Breathable, Plain Dyed, Thickness: Regular, Pattern Type: Striped, Size up to 3XL",
      "quantity": 8,
      "price_item": 19,
      "subtotal": 152
    },
    {
      "id": "OUT1622472147",
      "total_price": 927,
      "total_item": 3,
      "date": "2021-05-31 20:27:52",
      "is_cash": "Cash",
      "pay_deadline_date": "",
      "supplier_id": "CUST0004",
      "supplier_name": "Thomas Edward",
      "supplier_phone": 7036464680,
      "supplier_address": "4101  Sarah Drive",
      "category_name": "Console",
      "product_id": "NS69",
      "product_name": "Nintendo Switch",
      "product_desc": "Dimensions: 4 x 9.5 x 5.4 inch(W x L x H) with Joy-Cons, GPU: 768MHz (docked)/307.2MHz (undocked) Nvidia custom Tegra SOC, RAM: 4 GB, Max Resolution: docked 720p, undocked 1080p, Optical Drive: None, Storage: 32GB (expandable), Portable battery life: approx 3 - 7 hours",
      "quantity": 3,
      "price_item": 309,
      "subtotal": 927
    },
    {
      "id": "OUT1622467272",
      "total_price": 2219,
      "total_item": 1,
      "date": "2021-05-31 19:06:29",
      "is_cash": "Pay Later",
      "pay_deadline_date": "2021-06-30",
      "supplier_id": "CUST0002",
      "supplier_name": "Benedict Sauls",
      "supplier_phone": 7102450001,
      "supplier_address": "2041  Wildwood Street",
      "category_name": "Computers",
      "product_id": "DPT7",
      "product_name": "Dell Precision 7920 Tower",
      "product_desc": "Dual-CPU monster for tasks that can leverage its server-grade hardware and require maximum reliability. Just be prepared for sticker shock if you go all-in like on our test model.",
      "quantity": 1,
      "price_item": 2219,
      "subtotal": 2219
    },
    {
      "id": "OUT1622466842",
      "total_price": 1200,
      "total_item": 1,
      "date": "2021-05-31 18:59:38",
      "is_cash": "Cash",
      "pay_deadline_date": "",
      "supplier_id": "CUST0003",
      "supplier_name": "Emily Myers",
      "supplier_phone": 7021456969,
      "supplier_address": "871  Mandan Road",
      "category_name": "Smart Phones",
      "product_id": "SG21",
      "product_name": "Samsung Galaxy S21 Ultra",
      "product_desc": "Weight: 227g, Dimensions: 165.1 x 75.6 x 8.9 mm, OS: Android 11, Screen size: 6.8-inch, Resolution: 1440 x 3200, CPU: Snapdragon 888 / Exynos 2100, RAM: 12GB / 16GB, Storage: 128GB/256GB/512GB, Battery: 5,000mAh, Rear camera: 108MP + 10MP + 10MP + 12MP, Front camera: 40MP",
      "quantity": 1,
      "price_item": 1200,
      "subtotal": 1200
    }
  ]
}
